poxiaoai/__init__.py
poxiaoai/auth.py
poxiaoai/commands.py
poxiaoai/core.py
poxiaoai/np_log.py
poxiaoai-1.0.2.dist-info/METADATA
poxiaoai-1.0.2.dist-info/WHEEL
poxiaoai-1.0.2.dist-info/entry_points.txt
poxiaoai-1.0.2.dist-info/top_level.txt
poxiaoai-1.0.2.dist-info/RECORD
